baseresourcelib/__init__.py
baseresourcelib/bases/__init__.py
baseresourcelib/bases/base.py
baseresourcelib/connectors/__init__.py
baseresourcelib/connectors/base.py
baseresourcelib/connectors/brlbase.py
baseresourcelib/connectors/mongobase.py
baseresourcelib/connectors/responseobjects.py
baseresourcelib/errors/__init__.py
baseresourcelib/errors/errors.py
baseresourcelib/fields/__init__.py
baseresourcelib/fields/fields.py
baseresourcelib/utils/__init__.py
baseresourcelib/utils/constants.py
baseresourcelib/utils/decorators.py
baseresourcelib/utils/utils.py
baseresourcelib-0.0.3.dist-info/METADATA
baseresourcelib-0.0.3.dist-info/WHEEL
baseresourcelib-0.0.3.dist-info/licenses/LICENSE
baseresourcelib-0.0.3.dist-info/RECORD
